rsp/__init__.py
rsp/ml/__init__.py
rsp/ml/dataset/__init__.py
rsp/ml/dataset/dataset.py
rsp/ml/dataset/links/kinetics/annotations/k400_annotations.txt
rsp/ml/dataset/links/kinetics/paths/k400_test_path.txt
rsp/ml/dataset/links/kinetics/paths/k400_train_path.txt
rsp/ml/dataset/links/kinetics/paths/k400_val_path.txt
rsp/ml/metrics/__init__.py
rsp/ml/metrics/metrics.py
rsp/ml/model/__init__.py
rsp/ml/model/model.py
rsp/ml/module/__init__.py
rsp/ml/module/module.py
rsp/ml/multi_transforms/__init__.py
rsp/ml/multi_transforms/multi_transforms.py
rsp/ml/run/__init__.py
rsp/ml/run/run.py
rsp_ml-0.0.149.dist-info/LICENSE
rsp_ml-0.0.149.dist-info/METADATA
rsp_ml-0.0.149.dist-info/WHEEL
rsp_ml-0.0.149.dist-info/top_level.txt
rsp_ml-0.0.149.dist-info/RECORD
