Metadata-Version: 2.1
Name: rsp-ml
Version: 0.0.149
Summary: Machine Learning
Home-page: https://github.com/SchulzR97/rsp-ml
Author: Robert Schulz
Author-email: schulzr256@gmail.com
License: MIT
Keywords: python,Machine Learning
Classifier: Development Status :: 3 - Alpha
Classifier: Intended Audience :: Education
Classifier: Programming Language :: Python :: 2
Classifier: Programming Language :: Python :: 3
Classifier: Operating System :: MacOS :: MacOS X
Classifier: Operating System :: Microsoft :: Windows
Classifier: Operating System :: POSIX :: Linux
License-File: LICENSE
Requires-Dist: torch
Requires-Dist: torchvision
Requires-Dist: rsp-common >=0.0.29
Requires-Dist: numpy
Requires-Dist: opencv-python
Requires-Dist: pandas
Requires-Dist: seaborn
Requires-Dist: googledriver
Requires-Dist: huggingface-hub
Requires-Dist: ultralytics
Requires-Dist: datasets
Requires-Dist: gdown
Requires-Dist: platformdirs
